{"namedChunkGroups":{"polyfill":{"name":"polyfill","assets":[{"name":"webpack-runtime-3b6e8c71436c75685704.js","size":3167},{"name":"polyfill-c6ec331035a9dabcafe9.js","size":82619}],"filteredAssets":0,"assetsSize":85786,"filteredAuxiliaryAssets":2,"auxiliaryAssetsSize":214375},"app":{"name":"app","assets":[{"name":"webpack-runtime-3b6e8c71436c75685704.js","size":3167},{"name":"framework-d198ffde43ce26310b06.js","size":128866},{"name":"styles.2fa3f6b7d46af0752203.css","size":2828},{"name":"app-7bb565c6a1bffd16fa72.js","size":72053}],"filteredAssets":0,"assetsSize":206914,"filteredAuxiliaryAssets":3,"auxiliaryAssetsSize":610082},"component---src-pages-404-tsx":{"name":"component---src-pages-404-tsx","assets":[{"name":"component---src-pages-404-tsx-5ba1702132f43761cd24.js","size":797}],"filteredAssets":0,"assetsSize":797,"filteredAuxiliaryAssets":1,"auxiliaryAssetsSize":1951},"component---src-pages-index-tsx":{"name":"component---src-pages-index-tsx","assets":[{"name":"component---src-pages-index-tsx-2e06c58241dfc81cc80c.js","size":4384}],"filteredAssets":0,"assetsSize":4384,"filteredAuxiliaryAssets":1,"auxiliaryAssetsSize":7594}},"assetsByChunkName":{"polyfill":["webpack-runtime-3b6e8c71436c75685704.js","polyfill-c6ec331035a9dabcafe9.js"],"app":["webpack-runtime-3b6e8c71436c75685704.js","framework-d198ffde43ce26310b06.js","styles.2fa3f6b7d46af0752203.css","app-7bb565c6a1bffd16fa72.js"],"component---src-pages-404-tsx":["component---src-pages-404-tsx-5ba1702132f43761cd24.js"],"component---src-pages-index-tsx":["component---src-pages-index-tsx-2e06c58241dfc81cc80c.js"]},"childAssetsByChunkName":{}}